[
  {
    "name": "Color 1",
    "hexcode": "#373854",
    "guild_id": 565257922356051973,
    "role_id": 655152734189649932,
    "index": 1
  },
  {
    "name": "Color 2",
    "hexcode": "#493267",
    "guild_id": 565257922356051973,
    "role_id": null,
    "index": 2
  },
  {
    "name": "Color 3",
    "hexcode": "#9e379f",
    "guild_id": 565257922356051973,
    "role_id": 655152662865510400,
    "index": 3
  },
  {
    "name": "Color 4",
    "hexcode": "#e86af0",
    "guild_id": 565257922356051973,
    "role_id": 655152684969754628,
    "index": 4
  },
  {
    "name": "Color 5",
    "hexcode": "#7bb3ff",
    "guild_id": 565257922356051973,
    "role_id": 655152660969685012,
    "index": 5
  }
]